cv_color_features/__init__.py
cv_color_features/utils.py
cv_color_features-1.5.1.dist-info/LICENSE
cv_color_features-1.5.1.dist-info/METADATA
cv_color_features-1.5.1.dist-info/WHEEL
cv_color_features-1.5.1.dist-info/top_level.txt
cv_color_features-1.5.1.dist-info/RECORD
