Metadata-Version: 2.1
Name: cv-color-features
Version: 1.5.1
Summary: Utility library to generate feature metrics from regions in color images.
Home-page: UNKNOWN
Author: Scott White
Author-email: UNKNOWN
License: BSD 2-Clause License
Platform: UNKNOWN
Requires-Dist: cv2-extras (>=0.5.4)
Requires-Dist: numpy (>=1.16)
Requires-Dist: opencv-python (>=4.1)
Requires-Dist: pandas (>=0.24)
Requires-Dist: scipy (>=1.2)
